README.md
setup.py
TurtleEssentials/TurtleEssentials.py
TurtleEssentials/__init__.py
TurtleEssentials.egg-info/PKG-INFO
TurtleEssentials.egg-info/SOURCES.txt
TurtleEssentials.egg-info/dependency_links.txt
TurtleEssentials.egg-info/top_level.txt