Metadata-Version: 2.1
Name: TurtleEssentials
Version: 0.0.8
Summary: Extention of the built in Turtle package
Author: Pai
Author-email: irisdamodder@gmail.com
Classifier: Programming Language :: Python :: 3
Classifier: License :: OSI Approved :: MIT License
Classifier: Operating System :: OS Independent
Requires-Python: >=3.8
